{
  "events": {
    "ticket.created": {
      "key": "ticket.created",
      "event_key": "ticket.created",
      "label": "Ticket Created",
      "description": "A new support ticket has been created",
      "enabled": true,
      "roles": ["client", "admin", "support"],
      "channels": ["in_app", "email"],
      "priority": 6,
      "templates": {}
    },
    "ticket.assigned": {
      "key": "ticket.assigned",
      "event_key": "ticket.assigned",
      "label": "Ticket Assigned",
      "description": "A ticket has been assigned to a support agent",
      "enabled": true,
      "roles": ["admin", "support"],
      "channels": ["in_app", "email"],
      "priority": 7,
      "templates": {}
    },
    "ticket.updated": {
      "key": "ticket.updated",
      "event_key": "ticket.updated",
      "label": "Ticket Updated",
      "description": "A ticket has been updated",
      "enabled": true,
      "roles": ["client", "admin", "support"],
      "channels": ["in_app", "email"],
      "priority": 5,
      "templates": {}
    },
    "ticket.message_added": {
      "key": "ticket.message_added",
      "event_key": "ticket.message_added",
      "label": "New Ticket Message",
      "description": "A new message has been added to a ticket",
      "enabled": true,
      "roles": ["client", "admin", "support"],
      "channels": ["in_app", "email"],
      "priority": 6,
      "templates": {}
    },
    "ticket.attachment_uploaded": {
      "key": "ticket.attachment_uploaded",
      "event_key": "ticket.attachment_uploaded",
      "label": "Ticket Attachment Uploaded",
      "description": "A new attachment has been uploaded to a ticket",
      "enabled": true,
      "roles": ["client", "admin", "support"],
      "channels": ["in_app", "email"],
      "priority": 5,
      "templates": {}
    },
    "ticket.status_changed": {
      "key": "ticket.status_changed",
      "event_key": "ticket.status_changed",
      "label": "Ticket Status Changed",
      "description": "The status of a ticket has been changed",
      "enabled": true,
      "roles": ["client", "admin", "support"],
      "channels": ["in_app", "email"],
      "priority": 6,
      "templates": {}
    },
    "ticket.priority_changed": {
      "key": "ticket.priority_changed",
      "event_key": "ticket.priority_changed",
      "label": "Ticket Priority Changed",
      "description": "The priority of a ticket has been changed",
      "enabled": true,
      "roles": ["client", "admin", "support"],
      "channels": ["in_app", "email"],
      "priority": 6,
      "templates": {}
    },
    "ticket.resolved": {
      "key": "ticket.resolved",
      "event_key": "ticket.resolved",
      "label": "Ticket Resolved",
      "description": "A ticket has been resolved",
      "enabled": true,
      "roles": ["client", "admin", "support"],
      "channels": ["in_app", "email"],
      "priority": 8,
      "templates": {}
    },
    "ticket.reopened": {
      "key": "ticket.reopened",
      "event_key": "ticket.reopened",
      "label": "Ticket Reopened",
      "description": "A ticket has been reopened",
      "enabled": true,
      "roles": ["client", "admin", "support"],
      "channels": ["in_app", "email"],
      "priority": 6,
      "templates": {}
    },
    "ticket.closed": {
      "key": "ticket.closed",
      "event_key": "ticket.closed",
      "label": "Ticket Closed",
      "description": "A ticket has been closed",
      "enabled": true,
      "roles": ["client", "admin", "support"],
      "channels": ["in_app", "email"],
      "priority": 7,
      "templates": {}
    }
  }
}
